MANIFEST.in
README.rst
setup.cfg
setup.py
docs/HISTORY.txt
docs/INSTALL.txt
docs/LICENSE.GPL
docs/LICENSE.txt
pas/__init__.py
pas.plugins.velruse.egg-info/PKG-INFO
pas.plugins.velruse.egg-info/SOURCES.txt
pas.plugins.velruse.egg-info/dependency_links.txt
pas.plugins.velruse.egg-info/entry_points.txt
pas.plugins.velruse.egg-info/namespace_packages.txt
pas.plugins.velruse.egg-info/not-zip-safe
pas.plugins.velruse.egg-info/requires.txt
pas.plugins.velruse.egg-info/top_level.txt
pas/plugins/__init__.py
pas/plugins/velruse/__init__.py
pas/plugins/velruse/addform.pt
pas/plugins/velruse/config.py
pas/plugins/velruse/configure.zcml
pas/plugins/velruse/events.py
pas/plugins/velruse/fallback_requests.py
pas/plugins/velruse/interfaces.py
pas/plugins/velruse/persistent.py
pas/plugins/velruse/plugin.py
pas/plugins/velruse/setuphandlers.py
pas/plugins/velruse/browser/__init__.py
pas/plugins/velruse/browser/configure.zcml
pas/plugins/velruse/browser/controlpanel.pt
pas/plugins/velruse/browser/controlpanel.py
pas/plugins/velruse/browser/plugin_config.py
pas/plugins/velruse/browser/plugin_config_view.pt
pas/plugins/velruse/browser/images/facebook-login-icon.png
pas/plugins/velruse/browser/images/google-login-icon.png
pas/plugins/velruse/browser/images/linkedin-login-icon.png
pas/plugins/velruse/browser/images/openid.png
pas/plugins/velruse/browser/images/twitter-login-icon.png
pas/plugins/velruse/locales/pas.plugins.velruse-manual.pot
pas/plugins/velruse/locales/pas.plugins.velruse.pot
pas/plugins/velruse/locales/rebuildPo.sh
pas/plugins/velruse/locales/it/LC_MESSAGES/pas.plugins.velruse.mo
pas/plugins/velruse/locales/it/LC_MESSAGES/pas.plugins.velruse.po
pas/plugins/velruse/profiles/default/browserlayer.xml
pas/plugins/velruse/profiles/default/controlpanel.xml
pas/plugins/velruse/profiles/default/cssregistry.xml
pas/plugins/velruse/profiles/default/metadata.xml
pas/plugins/velruse/profiles/default/pas.plugins.velruse-various.txt
pas/plugins/velruse/profiles/default/registry.xml
pas/plugins/velruse/profiles/default/rolemap.xml
pas/plugins/velruse/profiles/default/skins.xml
pas/plugins/velruse/skins/pas.plugins.velruse/login_form.cpt
pas/plugins/velruse/skins/pas.plugins.velruse/login_form.cpt.metadata
pas/plugins/velruse/skins/pas.plugins.velruse/login_next.cpy
