Metadata-Version: 1.0
Name: pas.plugins.velruse
Version: 0.1.0a1
Summary: PAS plugin for Plone. Allow users to login using social networks through Velruse
Home-page: https://github.com/RedTurtle/pas.plugins.velruse
Author: RedTurtle Technology
Author-email: sviluppoplone@redturtle.it
License: GPL
Keywords: pas velruse plone authentication
Platform: UNKNOWN
Classifier: Development Status :: 3 - Alpha
Classifier: Framework :: Plone
Classifier: Framework :: Plone :: 3.3
Classifier: Framework :: Plone :: 4.0
Classifier: Framework :: Plone :: 4.1
Classifier: Framework :: Plone :: 4.2
Classifier: Framework :: Plone :: 4.3
Classifier: Programming Language :: Python
Classifier: Programming Language :: Python :: 2.6
Classifier: Programming Language :: Python :: 2.7
